MANIFEST.in
README.md
setup.py
bin/auroraex
src/auroraex/__init__.py
src/auroraex/commands.py
src/auroraex/core.py
src/auroraex/logger.py
src/auroraex/util.py
src/auroraex/validator.py
src/auroraex.egg-info/PKG-INFO
src/auroraex.egg-info/SOURCES.txt
src/auroraex.egg-info/dependency_links.txt
src/auroraex.egg-info/entry_points.txt
src/auroraex.egg-info/not-zip-safe
src/auroraex.egg-info/requires.txt
src/auroraex.egg-info/top_level.txt