Metadata-Version: 1.1
Name: auroraex
Version: 0.4.5
Summary: Command Line utility for Amazon Aurora.
Home-page: https://github.com/toyama0919/auroraex
Author: Hiroshi Toyama
Author-email: toyama0919@gmail.com
License: MIT
Keywords: amazon aurora aws mysql
Platform: UNKNOWN
Classifier: Programming Language :: Python :: 3.4
Classifier: Programming Language :: Python :: 3.5
Classifier: Programming Language :: Python :: 3.6
